<PAMDataset>
  <Metadata domain="IMAGE_STRUCTURE">
    <MDI key="COMPRESSION">JPEG</MDI>
    <MDI key="INTERLEAVE">PIXEL</MDI>
    <MDI key="SOURCE_COLOR_SPACE">YCbCr</MDI>
  </Metadata>
  <Metadata domain="xml:ESRI" format="xml">
    <GeodataXform xsi:type="typens:PolynomialXform" xmlns:xsi="http://www.w3.org/2001/XMLSchema-instance" xmlns:xs="http://www.w3.org/2001/XMLSchema" xmlns:typens="http://www.esri.com/schemas/ArcGIS/2.9.0">
      <PolynomialOrder>1</PolynomialOrder>
      <SpatialReference xsi:type="typens:ProjectedCoordinateSystem">
        <WKT>PROJCS["NAD_1983_2011_Oregon_Statewide_Lambert_Ft_Intl",GEOGCS["GCS_NAD_1983_2011",DATUM["D_NAD_1983_2011",SPHEROID["GRS_1980",6378137.0,298.257222101]],PRIMEM["Greenwich",0.0],UNIT["Degree",0.0174532925199433]],PROJECTION["Lambert_Conformal_Conic"],PARAMETER["False_Easting",1312335.958005249],PARAMETER["False_Northing",0.0],PARAMETER["Central_Meridian",-120.5],PARAMETER["Standard_Parallel_1",43.0],PARAMETER["Standard_Parallel_2",45.5],PARAMETER["Latitude_Of_Origin",41.75],UNIT["Foot",0.3048],AUTHORITY["EPSG",6557]]</WKT>
        <XOrigin>-118489100</XOrigin>
        <YOrigin>-97381100</YOrigin>
        <XYScale>37592196.316242374</XYScale>
        <ZOrigin>-100000</ZOrigin>
        <ZScale>10000</ZScale>
        <MOrigin>-100000</MOrigin>
        <MScale>10000</MScale>
        <XYTolerance>0.0032808398950131233</XYTolerance>
        <ZTolerance>0.001</ZTolerance>
        <MTolerance>0.001</MTolerance>
        <HighPrecision>true</HighPrecision>
        <WKID>102970</WKID>
        <LatestWKID>6557</LatestWKID>
      </SpatialReference>
      <SourceGCPs xsi:type="typens:ArrayOfDouble">
        <Double>2585.4127077172293</Double>
        <Double>-1628.0355536365146</Double>
        <Double>10441.629142933931</Double>
        <Double>-1847.1895316687485</Double>
        <Double>10010.50094695295</Double>
        <Double>-9772.4309531431645</Double>
        <Double>2165.7812587973981</Double>
        <Double>-9511.2270495314151</Double>
      </SourceGCPs>
      <TargetGCPs xsi:type="typens:ArrayOfDouble">
        <Double>626962.88845651667</Double>
        <Double>1513319.5482245234</Double>
        <Double>628272.58008851996</Double>
        <Double>1513283.4818774404</Double>
        <Double>628201.29126645031</Double>
        <Double>1511962.3100730132</Double>
        <Double>626893.66496215353</Double>
        <Double>1512004.9538439033</Double>
      </TargetGCPs>
      <Name />
    </GeodataXform>
  </Metadata>
</PAMDataset>
